tldr.py
multi_tldr-0.15.1.dist-info/LICENSE
multi_tldr-0.15.1.dist-info/METADATA
multi_tldr-0.15.1.dist-info/WHEEL
multi_tldr-0.15.1.dist-info/entry_points.txt
multi_tldr-0.15.1.dist-info/top_level.txt
multi_tldr-0.15.1.dist-info/RECORD
