Metadata-Version: 2.1
Name: multi-tldr
Version: 0.15.1
Summary: Yet another python client for tldr-pages/tldr. View tldr pages in multi repo, multi platform, any language at the same time.
Home-page: https://github.com/Phuker/multi-tldr
Author: Phuker
Author-email: Phuker@users.noreply.github.com
License: MIT
Keywords: tldr cli man command usage
Classifier: Environment :: Console
Classifier: Operating System :: POSIX
Classifier: Operating System :: POSIX :: Linux
Classifier: License :: OSI Approved :: MIT License
Classifier: Programming Language :: Python :: 3
Requires-Python: >=3.6
License-File: LICENSE
Requires-Dist: click (>=5.0)
